pytest_error_for_skips.py
pytest_error_for_skips-2.0.2.dist-info/LICENSE
pytest_error_for_skips-2.0.2.dist-info/METADATA
pytest_error_for_skips-2.0.2.dist-info/WHEEL
pytest_error_for_skips-2.0.2.dist-info/entry_points.txt
pytest_error_for_skips-2.0.2.dist-info/top_level.txt
pytest_error_for_skips-2.0.2.dist-info/RECORD
