Metadata-Version: 2.1
Name: pytest-error-for-skips
Version: 2.0.2
Summary: Pytest plugin to treat skipped tests a test failure
Home-page: https://github.com/jankatins/pytest-error-for-skips
Author: Jan Katins
Author-email: jasc@gmx.net
Maintainer: Jan Katins
Maintainer-email: jasc@gmx.net
License: MIT
Platform: UNKNOWN
Classifier: Development Status :: 4 - Beta
Classifier: Framework :: Pytest
Classifier: Intended Audience :: Developers
Classifier: Topic :: Software Development :: Testing
Classifier: Programming Language :: Python
Classifier: Programming Language :: Python :: 3
Classifier: Programming Language :: Python :: 3.5
Classifier: Programming Language :: Python :: 3.6
Classifier: Programming Language :: Python :: 3.7
Classifier: Programming Language :: Python :: 3.8
Classifier: Programming Language :: Python :: Implementation :: CPython
Classifier: Programming Language :: Python :: Implementation :: PyPy
Classifier: Operating System :: OS Independent
Classifier: License :: OSI Approved :: MIT License
Requires-Python: >=2.7, !=3.0.*, !=3.1.*, !=3.2.*
Requires-Dist: pytest (>=4.6)
